put_in_pocket.py
put_in_pocket-0.2.0.dist-info/entry_points.txt
put_in_pocket-0.2.0.dist-info/LICENSE
put_in_pocket-0.2.0.dist-info/WHEEL
put_in_pocket-0.2.0.dist-info/METADATA
put_in_pocket-0.2.0.dist-info/RECORD
