Metadata-Version: 2.1
Name: put_in_pocket
Version: 0.2.0
Summary: Command line app to add URLs to Pocket.
Author-email: Rhet Turnbull <rturnbull+git@gmail.com>
Requires-Python: >=3.9
Classifier: License :: OSI Approved :: MIT License
Requires-Dist: click >= 8.1.3
Requires-Dist: requests >= 2.28.2
Requires-Dist: rich >= 13.3.4
Requires-Dist: toml >= 0.10.2
Requires-Dist: xdg >= 6.0.0
Project-URL: Home, https://github.com/RhetTbull/put_in_pocket
